[
  {
    "date": "2026-03-13",
    "name": "S. RITHVIK",
    "class": "5TH",
    "receipt_no": "193",
    "payments": [
      [
        "ONLINE",
        8000
      ]
    ],
    "sheet": "RCB Feb to April 2025 26.pdf",
    "row": 1
  },
  {
    "date": "2026-03-13",
    "name": "S. AARADHYA",
    "class": "2ND",
    "receipt_no": "194",
    "payments": [
      [
        "ONLINE",
        9000
      ]
    ],
    "sheet": "RCB Feb to April 2025 26.pdf",
    "row": 2
  },
  {
    "date": "2026-03-13",
    "name": "P. VARSHITH",
    "class": "UKG",
    "receipt_no": "195",
    "payments": [
      [
        "CASH",
        5000
      ]
    ],
    "sheet": "RCB Feb to April 2025 26.pdf",
    "row": 3
  },
  {
    "date": "2026-03-13",
    "name": "P. SAANVIKA",
    "class": "2ND",
    "receipt_no": "196",
    "payments": [
      [
        "CASH",
        10000
      ]
    ],
    "sheet": "RCB Feb to April 2025 26.pdf",
    "row": 4
  },
  {
    "date": "2026-03-13",
    "name": "G. VEDAANSH",
    "class": "LKG",
    "receipt_no": "197",
    "payments": [
      [
        "ONLINE",
        6000
      ]
    ],
    "sheet": "RCB Feb to April 2025 26.pdf",
    "row": 5
  },
  {
    "date": "2026-03-13",
    "name": "G. RITHIKA",
    "class": "3RD",
    "receipt_no": "198",
    "payments": [
      [
        "ONLINE",
        12000
      ]
    ],
    "sheet": "RCB Feb to April 2025 26.pdf",
    "row": 6
  },
  {
    "date": "2026-03-13",
    "name": "M. HRITHIKA",
    "class": "1ST",
    "receipt_no": "199",
    "payments": [
      [
        "ONLINE",
        10000
      ]
    ],
    "sheet": "RCB Feb to April 2025 26.pdf",
    "row": 7
  },
  {
    "date": "2026-03-13",
    "name": "M. AKHIL",
    "class": "5TH",
    "receipt_no": "200",
    "payments": [
      [
        "CASH",
        15000
      ]
    ],
    "sheet": "RCB Feb to April 2025 26.pdf",
    "row": 8
  },
  {
    "date": "2026-03-14",
    "name": "A. NITHIN",
    "class": "7TH",
    "receipt_no": "201",
    "payments": [
      [
        "ONLINE",
        18000
      ]
    ],
    "sheet": "RCB Feb to April 2025 26.pdf",
    "row": 9
  },
  {
    "date": "2026-03-14",
    "name": "A. CHARAN",
    "class": "4TH",
    "receipt_no": "202",
    "payments": [
      [
        "ONLINE",
        10000
      ]
    ],
    "sheet": "RCB Feb to April 2025 26.pdf",
    "row": 10
  },
  {
    "date": "2026-03-14",
    "name": "K. VISHNU",
    "class": "3RD",
    "receipt_no": "203",
    "payments": [
      [
        "CASH",
        5000
      ]
    ],
    "sheet": "RCB Feb to April 2025 26.pdf",
    "row": 11
  },
  {
    "date": "2026-03-14",
    "name": "K. BHAVANI",
    "class": "UKG",
    "receipt_no": "204",
    "payments": [
      [
        "ONLINE",
        8000
      ]
    ],
    "sheet": "RCB Feb to April 2025 26.pdf",
    "row": 12
  },
  {
    "date": "2026-03-14",
    "name": "D. SAI TEJA",
    "class": "6TH",
    "receipt_no": "205",
    "payments": [
      [
        "ONLINE",
        12000
      ]
    ],
    "sheet": "RCB Feb to April 2025 26.pdf",
    "row": 13
  },
  {
    "date": "2026-03-14",
    "name": "D. AKSHAYA",
    "class": "4TH",
    "receipt_no": "206",
    "payments": [
      [
        "ONLINE",
        12000
      ]
    ],
    "sheet": "RCB Feb to April 2025 26.pdf",
    "row": 14
  },
  {
    "date": "2026-03-16",
    "name": "P. YASHIKA",
    "class": "2ND",
    "receipt_no": "207",
    "payments": [
      [
        "CASH",
        10000
      ]
    ],
    "sheet": "RCB Feb to April 2025 26.pdf",
    "row": 15
  },
  {
    "date": "2026-03-16",
    "name": "P. NIKHIL",
    "class": "UKG",
    "receipt_no": "208",
    "payments": [
      [
        "CASH",
        7000
      ]
    ],
    "sheet": "RCB Feb to April 2025 26.pdf",
    "row": 16
  },
  {
    "date": "2026-03-16",
    "name": "R. SRUJAN",
    "class": "5TH",
    "receipt_no": "209",
    "payments": [
      [
        "ONLINE",
        11000
      ]
    ],
    "sheet": "RCB Feb to April 2025 26.pdf",
    "row": 17
  },
  {
    "date": "2026-03-16",
    "name": "R. CHARAN",
    "class": "2ND",
    "receipt_no": "210",
    "payments": [
      [
        "ONLINE",
        9000
      ]
    ],
    "sheet": "RCB Feb to April 2025 26.pdf",
    "row": 18
  },
  {
    "date": "2026-03-16",
    "name": "B. THANVIKA",
    "class": "LKG",
    "receipt_no": "211",
    "payments": [
      [
        "ONLINE",
        6000
      ]
    ],
    "sheet": "RCB Feb to April 2025 26.pdf",
    "row": 19
  },
  {
    "date": "2026-03-16",
    "name": "B. DEEKSHITH",
    "class": "4TH",
    "receipt_no": "212",
    "payments": [
      [
        "ONLINE",
        13000
      ]
    ],
    "sheet": "RCB Feb to April 2025 26.pdf",
    "row": 20
  },
  {
    "date": "2026-03-17",
    "name": "M. SAI KIRAN",
    "class": "8TH",
    "receipt_no": "213",
    "payments": [
      [
        "CASH",
        20000
      ]
    ],
    "sheet": "RCB Feb to April 2025 26.pdf",
    "row": 21
  }
]